<?xml version="1.0" encoding="utf-8" ?><dwsync><file name="author-template.php" server="ftp.msleiman.co.uk" local="3443852974" remote="318763443829668312" Dst="-1" /><file name="bookmark-template.php" server="ftp.msleiman.co.uk" local="3443852974" remote="318763443829668312" Dst="-1" /><file name="bookmark.php" server="ftp.msleiman.co.uk" local="3443852974" remote="318763443829668312" Dst="-1" /><file name="cache.php" server="ftp.msleiman.co.uk" local="3443852974" remote="318763443829668312" Dst="-1" /><file name="capabilities.php" server="ftp.msleiman.co.uk" local="3443852974" remote="318763443829668312" Dst="-1" /><file name="category-template.php" server="ftp.msleiman.co.uk" local="3443852974" remote="318763443829668312" Dst="-1" /><file name="category.php" server="ftp.msleiman.co.uk" local="3443852974" remote="318763443829668312" Dst="-1" /><file name="class-IXR.php" server="ftp.msleiman.co.uk" local="3443852974" remote="318763443829668312" Dst="-1" /><file name="classes.php" server="ftp.msleiman.co.uk" local="3443852975" remote="318763443829668312" Dst="-1" /><file name="class-snoopy.php" server="ftp.msleiman.co.uk" local="3443852975" remote="318763443829668312" Dst="-1" /><file name="class-pop3.php" server="ftp.msleiman.co.uk" local="3443852975" remote="318763443829668312" Dst="-1" /><file name="comment-template.php" server="ftp.msleiman.co.uk" local="3443852975" remote="318763443829668312" Dst="-1" /><file name="comment.php" server="ftp.msleiman.co.uk" local="3443852975" remote="318763443829668312" Dst="-1" /><file name="compat.php" server="ftp.msleiman.co.uk" local="3443852975" remote="318763443829668312" Dst="-1" /><file name="cron.php" server="ftp.msleiman.co.uk" local="3443852975" remote="318763443829668312" Dst="-1" /><file name="default-filters.php" server="ftp.msleiman.co.uk" local="3443852976" remote="318763443829668312" Dst="-1" /><file name="deprecated.php" server="ftp.msleiman.co.uk" local="3443852976" remote="318763443829668312" Dst="-1" /><file name="feed.php" server="ftp.msleiman.co.uk" local="3443852976" remote="318763443829668312" Dst="-1" /><file name="formatting.php" server="ftp.msleiman.co.uk" local="3443852976" remote="318763443829668312" Dst="-1" /><file name="functions.php" server="ftp.msleiman.co.uk" local="3443852976" remote="318763443829668312" Dst="-1" /><file name="general-template.php" server="ftp.msleiman.co.uk" local="3443852976" remote="318763443829668312" Dst="-1" /><file name="gettext.php" server="ftp.msleiman.co.uk" local="3443852976" remote="318763443829668312" Dst="-1" /><file name="kses.php" server="ftp.msleiman.co.uk" local="3443853002" remote="318763443829668312" Dst="-1" /><file name="l10n.php" server="ftp.msleiman.co.uk" local="3443853002" remote="318763443829668312" Dst="-1" /><file name="link-template.php" server="ftp.msleiman.co.uk" local="3443853003" remote="318763443829668312" Dst="-1" /><file name="locale.php" server="ftp.msleiman.co.uk" local="3443853003" remote="318763443829668312" Dst="-1" /><file name="pluggable.php" server="ftp.msleiman.co.uk" local="3443853003" remote="318763443829668312" Dst="-1" /><file name="plugin.php" server="ftp.msleiman.co.uk" local="3443853003" remote="318763443829668312" Dst="-1" /><file name="post-template.php" server="ftp.msleiman.co.uk" local="3443853003" remote="318763443829668312" Dst="-1" /><file name="post.php" server="ftp.msleiman.co.uk" local="3443853004" remote="318763443829668312" Dst="-1" /><file name="registration-functions.php" server="ftp.msleiman.co.uk" local="3443853004" remote="318763443829668312" Dst="-1" /><file name="query.php" server="ftp.msleiman.co.uk" local="3443853004" remote="318763443829668312" Dst="-1" /><file name="registration.php" server="ftp.msleiman.co.uk" local="3443853004" remote="318763443829668312" Dst="-1" /><file name="rewrite.php" server="ftp.msleiman.co.uk" local="3443853004" remote="318763443829668312" Dst="-1" /><file name="rss-functions.php" server="ftp.msleiman.co.uk" local="3443853004" remote="318763443829668312" Dst="-1" /><file name="rss.php" server="ftp.msleiman.co.uk" local="3443853004" remote="318763443829668312" Dst="-1" /><file name="script-loader.php" server="ftp.msleiman.co.uk" local="3443853005" remote="318763443829668312" Dst="-1" /><file name="streams.php" server="ftp.msleiman.co.uk" local="3443853005" remote="318763443829668312" Dst="-1" /><file name="template-loader.php" server="ftp.msleiman.co.uk" local="3443853005" remote="318763443829668312" Dst="-1" /><file name="theme.php" server="ftp.msleiman.co.uk" local="3443853005" remote="318763443829668312" Dst="-1" /><file name="user.php" server="ftp.msleiman.co.uk" local="3443853005" remote="318763443829668312" Dst="-1" /><file name="version.php" server="ftp.msleiman.co.uk" local="3443853005" remote="318763443829668312" Dst="-1" /><file name="vars.php" server="ftp.msleiman.co.uk" local="3443853005" remote="318763443829668312" Dst="-1" /><file name="wp-db.php" server="ftp.msleiman.co.uk" local="3443853005" remote="318763443829668312" Dst="-1" /></dwsync>